[
{"sampleid":"18712","name":"001.swc"},
{"sampleid":"18712","name":"002.swc"},
{"sampleid":"18712","name":"004.swc"},
{"sampleid":"18712","name":"005.swc"},
{"sampleid":"18712","name":"006.swc"},
{"sampleid":"18712","name":"007.swc"},
{"sampleid":"18712","name":"008.swc"},
{"sampleid":"18712","name":"021.swc"},
{"sampleid":"18712","name":"022.swc"},
{"sampleid":"18712","name":"023.swc"},
{"sampleid":"18712","name":"024.swc"},
{"sampleid":"18712","name":"025.swc"},
{"sampleid":"18712","name":"026.swc"},
{"sampleid":"18712","name":"027.swc"},
{"sampleid":"18712","name":"028.swc"},
{"sampleid":"18712","name":"029.swc"},
{"sampleid":"18712","name":"031.swc"},
{"sampleid":"18712","name":"032.swc"},
{"sampleid":"18712","name":"036.swc"},
{"sampleid":"18712","name":"037.swc"},
{"sampleid":"18712","name":"038.swc"},
{"sampleid":"18712","name":"039.swc"},
{"sampleid":"18712","name":"040.swc"},
{"sampleid":"18712","name":"041.swc"},
{"sampleid":"18712","name":"042.swc"},
{"sampleid":"18712","name":"043.swc"},
{"sampleid":"18712","name":"044.swc"},
{"sampleid":"18712","name":"045.swc"},
{"sampleid":"18712","name":"046.swc"},
{"sampleid":"18712","name":"047.swc"},
{"sampleid":"18712","name":"048.swc"},
{"sampleid":"18712","name":"049.swc"},
{"sampleid":"18712","name":"050.swc"},
{"sampleid":"18712","name":"051.swc"},
{"sampleid":"18712","name":"052.swc"},
{"sampleid":"18712","name":"053.swc"},
{"sampleid":"18712","name":"054.swc"},
{"sampleid":"18712","name":"055.swc"},
{"sampleid":"18712","name":"056.swc"},
{"sampleid":"18712","name":"057.swc"},
{"sampleid":"18712","name":"058.swc"},
{"sampleid":"18712","name":"060.swc"},
{"sampleid":"18712","name":"061.swc"},
{"sampleid":"18712","name":"062.swc"},
{"sampleid":"18712","name":"063.swc"},
{"sampleid":"18712","name":"064.swc"},
{"sampleid":"18712","name":"065.swc"},
{"sampleid":"18712","name":"066.swc"},
{"sampleid":"18712","name":"068.swc"},
{"sampleid":"18712","name":"071.swc"},
{"sampleid":"18712","name":"072.swc"},
{"sampleid":"18712","name":"075.swc"},
{"sampleid":"18712","name":"076.swc"},
{"sampleid":"18713","name":"001.swc"},
{"sampleid":"18713","name":"004.swc"},
{"sampleid":"18713","name":"005.swc"},
{"sampleid":"18713","name":"006.swc"},
{"sampleid":"18713","name":"007.swc"},
{"sampleid":"18713","name":"008.swc"},
{"sampleid":"18713","name":"009.swc"},
{"sampleid":"18713","name":"010.swc"},
{"sampleid":"18713","name":"011.swc"},
{"sampleid":"18713","name":"012.swc"},
{"sampleid":"18713","name":"013.swc"},
{"sampleid":"18713","name":"014.swc"},
{"sampleid":"18713","name":"015.swc"},
{"sampleid":"18713","name":"016.swc"},
{"sampleid":"18713","name":"018.swc"},
{"sampleid":"18713","name":"019.swc"},
{"sampleid":"18713","name":"020.swc"},
{"sampleid":"18713","name":"021.swc"},
{"sampleid":"18713","name":"022.swc"},
{"sampleid":"18713","name":"023.swc"},
{"sampleid":"18713","name":"024.swc"},
{"sampleid":"18713","name":"025.swc"},
{"sampleid":"18713","name":"030.swc"},
{"sampleid":"18713","name":"031.swc"},
{"sampleid":"18713","name":"035.swc"},
{"sampleid":"18713","name":"036.swc"},
{"sampleid":"18713","name":"041.swc"},
{"sampleid":"18713","name":"045.swc"},
{"sampleid":"18713","name":"047.swc"},
{"sampleid":"18713","name":"048.swc"},
{"sampleid":"18713","name":"049.swc"},
{"sampleid":"18713","name":"050.swc"},
{"sampleid":"18713","name":"051.swc"},
{"sampleid":"18713","name":"052.swc"},
{"sampleid":"18713","name":"053.swc"},
{"sampleid":"18713","name":"055.swc"},
{"sampleid":"18713","name":"056.swc"},
{"sampleid":"18713","name":"061.swc"},
{"sampleid":"18713","name":"062.swc"},
{"sampleid":"18713","name":"063.swc"},
{"sampleid":"18713","name":"064.swc"},
{"sampleid":"18713","name":"065.swc"},
{"sampleid":"18713","name":"066.swc"},
{"sampleid":"18713","name":"068.swc"},
{"sampleid":"18713","name":"070.swc"},
{"sampleid":"18713","name":"072.swc"},
{"sampleid":"18713","name":"073.swc"},
{"sampleid":"18713","name":"074.swc"},
{"sampleid":"18713","name":"075.swc"},
{"sampleid":"18713","name":"076.swc"},
{"sampleid":"18713","name":"077.swc"},
{"sampleid":"18713","name":"078.swc"},
{"sampleid":"18713","name":"082.swc"},
{"sampleid":"18713","name":"083.swc"},
{"sampleid":"18713","name":"084.swc"},
{"sampleid":"18713","name":"085.swc"},
{"sampleid":"18714","name":"001.swc"},
{"sampleid":"18714","name":"002.swc"},
{"sampleid":"18714","name":"003.swc"},
{"sampleid":"18714","name":"004.swc"},
{"sampleid":"18714","name":"005.swc"},
{"sampleid":"18714","name":"006.swc"},
{"sampleid":"18714","name":"007.swc"},
{"sampleid":"18714","name":"008.swc"},
{"sampleid":"18714","name":"010.swc"},
{"sampleid":"18714","name":"012.swc"},
{"sampleid":"18714","name":"013.swc"},
{"sampleid":"18714","name":"014.swc"},
{"sampleid":"18714","name":"015.swc"},
{"sampleid":"18714","name":"019.swc"},
{"sampleid":"18714","name":"021.swc"},
{"sampleid":"18714","name":"022.swc"},
{"sampleid":"18714","name":"023.swc"},
{"sampleid":"18714","name":"024.swc"},
{"sampleid":"18714","name":"025.swc"},
{"sampleid":"18714","name":"026.swc"},
{"sampleid":"18714","name":"027.swc"},
{"sampleid":"18714","name":"028.swc"},
{"sampleid":"18714","name":"029.swc"},
{"sampleid":"18714","name":"030.swc"},
{"sampleid":"18714","name":"031.swc"},
{"sampleid":"18714","name":"032.swc"},
{"sampleid":"18714","name":"034.swc"},
{"sampleid":"18714","name":"035.swc"},
{"sampleid":"18714","name":"036.swc"},
{"sampleid":"18714","name":"038.swc"},
{"sampleid":"18714","name":"039.swc"},
{"sampleid":"18714","name":"040.swc"},
{"sampleid":"18714","name":"041.swc"},
{"sampleid":"18714","name":"043.swc"},
{"sampleid":"18714","name":"045.swc"},
{"sampleid":"18714","name":"046.swc"},
{"sampleid":"18714","name":"047.swc"},
{"sampleid":"18714","name":"048.swc"},
{"sampleid":"18714","name":"049.swc"},
{"sampleid":"18714","name":"050.swc"},
{"sampleid":"18714","name":"051.swc"},
{"sampleid":"18714","name":"052.swc"},
{"sampleid":"18714","name":"053.swc"},
{"sampleid":"18714","name":"054.swc"},
{"sampleid":"18714","name":"055.swc"},
{"sampleid":"18714","name":"056.swc"},
{"sampleid":"18714","name":"057.swc"},
{"sampleid":"18714","name":"059.swc"},
{"sampleid":"18714","name":"062.swc"},
{"sampleid":"18714","name":"063.swc"},
{"sampleid":"18714","name":"065.swc"},
{"sampleid":"18714","name":"067.swc"},
{"sampleid":"18714","name":"069.swc"},
{"sampleid":"18714","name":"070.swc"},
{"sampleid":"18714","name":"071.swc"},
{"sampleid":"18714","name":"072.swc"},
{"sampleid":"18714","name":"073.swc"},
{"sampleid":"18714","name":"074.swc"},
{"sampleid":"18714","name":"075.swc"},
{"sampleid":"18714","name":"076.swc"},
{"sampleid":"18714","name":"077.swc"},
{"sampleid":"18714","name":"083.swc"},
{"sampleid":"18714","name":"084.swc"},
{"sampleid":"18714","name":"085.swc"},
{"sampleid":"18714","name":"086.swc"},
{"sampleid":"18714","name":"087.swc"},
{"sampleid":"18714","name":"090.swc"},
{"sampleid":"18714","name":"093.swc"},
{"sampleid":"18714","name":"094.swc"},
{"sampleid":"18714","name":"095.swc"},
{"sampleid":"18714","name":"101.swc"},
{"sampleid":"18714","name":"103.swc"},
{"sampleid":"18714","name":"105.swc"},
{"sampleid":"18714","name":"106.swc"},
{"sampleid":"18714","name":"109.swc"},
{"sampleid":"18714","name":"110.swc"},
{"sampleid":"18714","name":"112.swc"},
{"sampleid":"18714","name":"113.swc"},
{"sampleid":"18714","name":"114.swc"},
{"sampleid":"18714","name":"115.swc"},
{"sampleid":"18714","name":"119.swc"},
{"sampleid":"18714","name":"122.swc"},
{"sampleid":"18714","name":"123.swc"},
{"sampleid":"18714","name":"124.swc"},
{"sampleid":"18714","name":"125.swc"},
{"sampleid":"18714","name":"126.swc"},
{"sampleid":"18714","name":"127.swc"},
{"sampleid":"18714","name":"128.swc"},
{"sampleid":"18715","name":"001.swc"},
{"sampleid":"18715","name":"002.swc"},
{"sampleid":"18715","name":"003.swc"},
{"sampleid":"18715","name":"004.swc"},
{"sampleid":"18715","name":"005.swc"},
{"sampleid":"18715","name":"007.swc"},
{"sampleid":"18715","name":"009.swc"},
{"sampleid":"18715","name":"010.swc"},
{"sampleid":"18715","name":"011.swc"},
{"sampleid":"18715","name":"013.swc"},
{"sampleid":"18715","name":"015.swc"},
{"sampleid":"18715","name":"018.swc"},
{"sampleid":"18715","name":"019.swc"},
{"sampleid":"18715","name":"020.swc"},
{"sampleid":"18715","name":"021.swc"},
{"sampleid":"18715","name":"024.swc"},
{"sampleid":"18715","name":"025.swc"},
{"sampleid":"18715","name":"026.swc"},
{"sampleid":"18715","name":"027.swc"},
{"sampleid":"18715","name":"028.swc"},
{"sampleid":"18715","name":"030.swc"},
{"sampleid":"18715","name":"032.swc"},
{"sampleid":"18715","name":"033.swc"},
{"sampleid":"18715","name":"034.swc"},
{"sampleid":"18715","name":"035.swc"},
{"sampleid":"18715","name":"036.swc"},
{"sampleid":"18715","name":"037.swc"},
{"sampleid":"18715","name":"039.swc"},
{"sampleid":"18715","name":"057.swc"},
{"sampleid":"18715","name":"059.swc"},
{"sampleid":"18715","name":"060.swc"},
{"sampleid":"18715","name":"065.swc"},
{"sampleid":"18715","name":"067.swc"}
]
